INSTALL.rst
MANIFEST.in
README.rst
VERSION
setup.cfg
setup.py
src/pykor/__init__.py
src/pykor/__main__.py
src/pykor/__meta__.py
src/pykor/keywords.py
src/pykor/transpyler.py
src/pykor.egg-info/PKG-INFO
src/pykor.egg-info/SOURCES.txt
src/pykor.egg-info/dependency_links.txt
src/pykor.egg-info/entry_points.txt
src/pykor.egg-info/not-zip-safe
src/pykor.egg-info/requires.txt
src/pykor.egg-info/top_level.txt
src/pykor/tests/__init__.py