Metadata-Version: 1.1
Name: pykor
Version: 0.1.0
Summary: 한국의 파이썬 인터프리터.
Home-page: https://github.com/transpyler/pykor
Author: Jiyoung Hwang
Author-email: jy.hwng@gmail.com
License: UNKNOWN
Platform: UNKNOWN
Classifier: Development Status :: 3 - Alpha
Classifier: Intended Audience :: Developers
Classifier: License :: OSI Approved :: GNU General Public License (GPL)
Classifier: Operating System :: POSIX
Classifier: Programming Language :: Python
Classifier: Topic :: Software Development :: Libraries
